README.rst
setup.cfg
setup.py
django_mutpy/__init__.py
django_mutpy/django_compat.py
django_mutpy/models.py
django_mutpy/mutpy_runner.py
django_mutpy/utils.py
django_mutpy.egg-info/PKG-INFO
django_mutpy.egg-info/SOURCES.txt
django_mutpy.egg-info/dependency_links.txt
django_mutpy.egg-info/not-zip-safe
django_mutpy.egg-info/requires.txt
django_mutpy.egg-info/top_level.txt
django_mutpy/management/__init__.py
django_mutpy/management/commands/__init__.py
django_mutpy/management/commands/muttest.py