Metadata-Version: 1.1
Name: django-mutpy
Version: 0.1.2
Summary: Mutation testing with MutPy for Django.
Home-page: https://github.com/phihos/django-mutpy
Author: Philipp Hossner
Author-email: philipp.hossner@posteo.de
License: Apache 2.0
Platform: UNKNOWN
Classifier: Environment :: Web Environment
Classifier: Intended Audience :: Developers
Classifier: Operating System :: OS Independent
Classifier: Programming Language :: Python
Classifier: Programming Language :: Python :: 3.3
Classifier: Programming Language :: Python :: 3.4
Classifier: Programming Language :: Python :: 3.5
Classifier: Programming Language :: Python :: 3.6
Classifier: Framework :: Django
